LICENSE
MANIFEST.in
README.md
setup.py
gelfclient/__init__.py
gelfclient/client.py
larrabee_gelfclient.egg-info/PKG-INFO
larrabee_gelfclient.egg-info/SOURCES.txt
larrabee_gelfclient.egg-info/dependency_links.txt
larrabee_gelfclient.egg-info/requires.txt
larrabee_gelfclient.egg-info/top_level.txt