Metadata-Version: 1.1
Name: larrabee-gelfclient
Version: 0.0.6
Summary: A UDP client for sending message in the Graylog Extended Log Format (GELF)
Home-page: http://github.com/orionvm/python-gelfclient
Author: Chris McClymont
Author-email: chris@mcclymont.it
License: Apache v2
Keywords: gelf,graylog,graylog2,logging
Platform: UNKNOWN
Classifier: Development Status :: 3 - Alpha
Classifier: Topic :: Utilities
Classifier: Topic :: System :: Logging
